<?xml version="1.0" encoding="UTF-8"?>
<objects serializationModel="Studio.02.00.00">
	<object class="AudioFile" id="{0c0fc175-002a-46f4-9fbb-17ebb60df4b1}">
		<property name="assetPath">
			<value>boiling1.wav</value>
		</property>
		<property name="frequencyInKHz">
			<value>44.0999985</value>
		</property>
		<property name="channelCount">
			<value>2</value>
		</property>
		<property name="length">
			<value>2.2186167800453513</value>
		</property>
		<relationship name="masterAssetFolder">
			<destination>{fe45c7e2-30b6-4f62-9ae2-6f03556916f2}</destination>
		</relationship>
	</object>
</objects>
